jupyterlab_extension_theme_onedark/__init__.py
jupyterlab_extension_theme_onedark/_version.py
jupyterlab_extension_theme_onedark-0.1.0.data/data/share/jupyter/labextensions/jupyterlab-extension-theme-onedark/package.json
jupyterlab_extension_theme_onedark-0.1.0.data/data/share/jupyter/labextensions/jupyterlab-extension-theme-onedark/static/568.94442a36f1c354d4f2fe.js
jupyterlab_extension_theme_onedark-0.1.0.data/data/share/jupyter/labextensions/jupyterlab-extension-theme-onedark/static/remoteEntry.c90f3ba965dbc5fc7050.js
jupyterlab_extension_theme_onedark-0.1.0.data/data/share/jupyter/labextensions/jupyterlab-extension-theme-onedark/static/style.js
jupyterlab_extension_theme_onedark-0.1.0.data/data/share/jupyter/labextensions/jupyterlab-extension-theme-onedark/static/third-party-licenses.json
jupyterlab_extension_theme_onedark-0.1.0.data/data/share/jupyter/labextensions/jupyterlab-extension-theme-onedark/themes/jupyterlab-extension-theme-onedark/index.css
jupyterlab_extension_theme_onedark-0.1.0.data/data/share/jupyter/labextensions/jupyterlab-extension-theme-onedark/themes/jupyterlab-extension-theme-onedark/index.js
jupyterlab_extension_theme_onedark-0.1.0.data/data/share/jupyter/labextensions/jupyterlab-extension-theme-onedark/install.json
jupyterlab_extension_theme_onedark-0.1.0.dist-info/METADATA
jupyterlab_extension_theme_onedark-0.1.0.dist-info/WHEEL
jupyterlab_extension_theme_onedark-0.1.0.dist-info/licenses/LICENSE
jupyterlab_extension_theme_onedark-0.1.0.dist-info/RECORD
