Metadata-Version: 2.1
Name: jupyterlab_extension_theme_onedark
Version: 0.1.0
Summary: A JupyterLab extension theme as vscode onedark
Project-URL: Homepage, https://code.alibaba-inc.com/msd/jupyterlab-plugins
Project-URL: Bug Tracker, https://code.alibaba-inc.com/msd/jupyterlab-plugins/issues
Project-URL: Repository, https://code.alibaba-inc.com/msd/jupyterlab-plugins.git
Author-email: "guixia.lgx" <guixia.lgx@alibaba-inc.com>
License: BSD 3-Clause License
License-File: LICENSE
Classifier: Framework :: Jupyter
Classifier: Framework :: Jupyter :: JupyterLab
Classifier: Framework :: Jupyter :: JupyterLab :: 4
Classifier: Framework :: Jupyter :: JupyterLab :: Extensions
Classifier: Framework :: Jupyter :: JupyterLab :: Extensions :: Prebuilt
Classifier: License :: OSI Approved :: BSD License
Classifier: Programming Language :: Python
Classifier: Programming Language :: Python :: 3
Classifier: Programming Language :: Python :: 3.8
Classifier: Programming Language :: Python :: 3.9
Classifier: Programming Language :: Python :: 3.10
Classifier: Programming Language :: Python :: 3.11
Requires-Python: >=3.8
